<?xml version="1.0" encoding="UTF-8"?>

<!-- generated on 2021-06-14 13:42:22 by Eclipse SUMO netedit Version UNKNOWN
<configuration xmlns:xsi="http://www.w3.org/2001/XMLSchema-instance" xsi:noNamespaceSchemaLocation="http://sumo.dlr.de/xsd/netconvertConfiguration.xsd">

    <output>
        <output-file value="/home/romain/Documents/code/dqn/atsc-dqn/env/custom_env/data/2x2_3tls_a/2x2_3tls_a.net.xml"/>
    </output>

    <processing>
        <offset.disable-normalization value="true"/>
    </processing>

    <junctions>
        <no-turnarounds value="true"/>
    </junctions>

    <report>
        <aggregate-warnings value="5"/>
    </report>

</configuration>
-->

<net version="1.9" junctionCornerDetail="5" limitTurnSpeed="5.50" xmlns:xsi="http://www.w3.org/2001/XMLSchema-instance" xsi:noNamespaceSchemaLocation="http://sumo.dlr.de/xsd/net_file.xsd">

    <location netOffset="0.00,0.00" convBoundary="-400.00,-200.00,400.00,200.00" origBoundary="10000000000.00,10000000000.00,-10000000000.00,-10000000000.00" projParameter="!"/>

    <edge id=":gneJ1_0" function="internal">
        <lane id=":gneJ1_0_0" index="0" speed="6.51" length="9.03" shape="-204.80,10.40 -205.15,7.95 -206.20,6.20 -207.95,5.15 -210.40,4.80"/>
    </edge>
    <edge id=":gneJ1_1" function="internal">
        <lane id=":gneJ1_1_0" index="0" speed="13.89" length="20.80" shape="-204.80,10.40 -204.80,-10.40"/>
        <lane id=":gneJ1_1_1" index="1" speed="13.89" length="20.80" shape="-201.60,10.40 -201.60,-10.40"/>
    </edge>
    <edge id=":gneJ1_3" function="internal">
        <lane id=":gneJ1_3_0" index="0" speed="9.26" length="6.96" shape="-201.60,10.40 -200.85,5.15 -200.00,3.73"/>
    </edge>
    <edge id=":gneJ1_16" function="internal">
        <lane id=":gneJ1_16_0" index="0" speed="9.26" length="12.40" shape="-200.00,3.73 -198.60,1.40 -194.85,-0.85 -189.60,-1.60"/>
    </edge>
    <edge id=":gneJ1_4" function="internal">
        <lane id=":gneJ1_4_0" index="0" speed="6.51" length="9.03" shape="-189.60,4.80 -192.05,5.15 -193.80,6.20 -194.85,7.95 -195.20,10.40"/>
    </edge>
    <edge id=":gneJ1_5" function="internal">
        <lane id=":gneJ1_5_0" index="0" speed="13.89" length="20.80" shape="-189.60,4.80 -210.40,4.80"/>
        <lane id=":gneJ1_5_1" index="1" speed="13.89" length="20.80" shape="-189.60,1.60 -210.40,1.60"/>
    </edge>
    <edge id=":gneJ1_7" function="internal">
        <lane id=":gneJ1_7_0" index="0" speed="9.26" length="6.96" shape="-189.60,1.60 -194.85,0.85 -196.27,0.00"/>
    </edge>
    <edge id=":gneJ1_17" function="internal">
        <lane id=":gneJ1_17_0" index="0" speed="9.26" length="12.40" shape="-196.27,0.00 -198.60,-1.40 -200.85,-5.15 -201.60,-10.40"/>
    </edge>
    <edge id=":gneJ1_8" function="internal">
        <lane id=":gneJ1_8_0" index="0" speed="6.51" length="9.03" shape="-195.20,-10.40 -194.85,-7.95 -193.80,-6.20 -192.05,-5.15 -189.60,-4.80"/>
    </edge>
    <edge id=":gneJ1_9" function="internal">
        <lane id=":gneJ1_9_0" index="0" speed="13.89" length="20.80" shape="-195.20,-10.40 -195.20,10.40"/>
        <lane id=":gneJ1_9_1" index="1" speed="13.89" length="20.80" shape="-198.40,-10.40 -198.40,10.40"/>
    </edge>
    <edge id=":gneJ1_11" function="internal">
        <lane id=":gneJ1_11_0" index="0" speed="9.26" length="6.96" shape="-198.40,-10.40 -199.15,-5.15 -200.00,-3.73"/>
    </edge>
    <edge id=":gneJ1_18" function="internal">
        <lane id=":gneJ1_18_0" index="0" speed="9.26" length="12.40" shape="-200.00,-3.73 -201.40,-1.40 -205.15,0.85 -210.40,1.60"/>
    </edge>
    <edge id=":gneJ1_12" function="internal">
        <lane id=":gneJ1_12_0" index="0" speed="6.51" length="9.03" shape="-210.40,-4.80 -207.95,-5.15 -206.20,-6.20 -205.15,-7.95 -204.80,-10.40"/>
    </edge>
    <edge id=":gneJ1_13" function="internal">
        <lane id=":gneJ1_13_0" index="0" speed="13.89" length="20.80" shape="-210.40,-4.80 -189.60,-4.80"/>
        <lane id=":gneJ1_13_1" index="1" speed="13.89" length="20.80" shape="-210.40,-1.60 -189.60,-1.60"/>
    </edge>
    <edge id=":gneJ1_15" function="internal">
        <lane id=":gneJ1_15_0" index="0" speed="9.26" length="6.96" shape="-210.40,-1.60 -205.15,-0.85 -203.73,-0.00"/>
    </edge>
    <edge id=":gneJ1_19" function="internal">
        <lane id=":gneJ1_19_0" index="0" speed="9.26" length="12.40" shape="-203.73,-0.00 -201.40,1.40 -199.15,5.15 -198.40,10.40"/>
    </edge>
    <edge id=":gneJ4_0" function="internal">
        <lane id=":gneJ4_0_0" index="0" speed="6.51" length="9.03" shape="-4.80,10.40 -5.15,7.95 -6.20,6.20 -7.95,5.15 -10.40,4.80"/>
    </edge>
    <edge id=":gneJ4_1" function="internal">
        <lane id=":gneJ4_1_0" index="0" speed="13.89" length="20.80" shape="-4.80,10.40 -4.80,-10.40"/>
        <lane id=":gneJ4_1_1" index="1" speed="13.89" length="20.80" shape="-1.60,10.40 -1.60,-10.40"/>
    </edge>
    <edge id=":gneJ4_3" function="internal">
        <lane id=":gneJ4_3_0" index="0" speed="9.26" length="6.96" shape="-1.60,10.40 -0.85,5.15 -0.00,3.73"/>
    </edge>
    <edge id=":gneJ4_16" function="internal">
        <lane id=":gneJ4_16_0" index="0" speed="9.26" length="12.40" shape="-0.00,3.73 1.40,1.40 5.15,-0.85 10.40,-1.60"/>
    </edge>
    <edge id=":gneJ4_4" function="internal">
        <lane id=":gneJ4_4_0" index="0" speed="6.51" length="9.03" shape="10.40,4.80 7.95,5.15 6.20,6.20 5.15,7.95 4.80,10.40"/>
    </edge>
    <edge id=":gneJ4_5" function="internal">
        <lane id=":gneJ4_5_0" index="0" speed="13.89" length="20.80" shape="10.40,4.80 -10.40,4.80"/>
        <lane id=":gneJ4_5_1" index="1" speed="13.89" length="20.80" shape="10.40,1.60 -10.40,1.60"/>
    </edge>
    <edge id=":gneJ4_7" function="internal">
        <lane id=":gneJ4_7_0" index="0" speed="9.26" length="6.96" shape="10.40,1.60 5.15,0.85 3.73,0.00"/>
    </edge>
    <edge id=":gneJ4_17" function="internal">
        <lane id=":gneJ4_17_0" index="0" speed="9.26" length="12.40" shape="3.73,0.00 1.40,-1.40 -0.85,-5.15 -1.60,-10.40"/>
    </edge>
    <edge id=":gneJ4_8" function="internal">
        <lane id=":gneJ4_8_0" index="0" speed="6.51" length="9.03" shape="4.80,-10.40 5.15,-7.95 6.20,-6.20 7.95,-5.15 10.40,-4.80"/>
    </edge>
    <edge id=":gneJ4_9" function="internal">
        <lane id=":gneJ4_9_0" index="0" speed="13.89" length="20.80" shape="4.80,-10.40 4.80,10.40"/>
        <lane id=":gneJ4_9_1" index="1" speed="13.89" length="20.80" shape="1.60,-10.40 1.60,10.40"/>
    </edge>
    <edge id=":gneJ4_11" function="internal">
        <lane id=":gneJ4_11_0" index="0" speed="9.26" length="6.96" shape="1.60,-10.40 0.85,-5.15 0.00,-3.73"/>
    </edge>
    <edge id=":gneJ4_18" function="internal">
        <lane id=":gneJ4_18_0" index="0" speed="9.26" length="12.40" shape="0.00,-3.73 -1.40,-1.40 -5.15,0.85 -10.40,1.60"/>
    </edge>
    <edge id=":gneJ4_12" function="internal">
        <lane id=":gneJ4_12_0" index="0" speed="6.51" length="9.03" shape="-10.40,-4.80 -7.95,-5.15 -6.20,-6.20 -5.15,-7.95 -4.80,-10.40"/>
    </edge>
    <edge id=":gneJ4_13" function="internal">
        <lane id=":gneJ4_13_0" index="0" speed="13.89" length="20.80" shape="-10.40,-4.80 10.40,-4.80"/>
        <lane id=":gneJ4_13_1" index="1" speed="13.89" length="20.80" shape="-10.40,-1.60 10.40,-1.60"/>
    </edge>
    <edge id=":gneJ4_15" function="internal">
        <lane id=":gneJ4_15_0" index="0" speed="9.26" length="6.96" shape="-10.40,-1.60 -5.15,-0.85 -3.73,-0.00"/>
    </edge>
    <edge id=":gneJ4_19" function="internal">
        <lane id=":gneJ4_19_0" index="0" speed="9.26" length="12.40" shape="-3.73,-0.00 -1.40,1.40 0.85,5.15 1.60,10.40"/>
    </edge>
    <edge id=":gneJ6_0" function="internal">
        <lane id=":gneJ6_0_0" index="0" speed="6.51" length="9.03" shape="195.20,10.40 194.85,7.95 193.80,6.20 192.05,5.15 189.60,4.80"/>
    </edge>
    <edge id=":gneJ6_1" function="internal">
        <lane id=":gneJ6_1_0" index="0" speed="13.89" length="20.80" shape="195.20,10.40 195.20,-10.40"/>
        <lane id=":gneJ6_1_1" index="1" speed="13.89" length="20.80" shape="198.40,10.40 198.40,-10.40"/>
    </edge>
    <edge id=":gneJ6_3" function="internal">
        <lane id=":gneJ6_3_0" index="0" speed="9.26" length="6.96" shape="198.40,10.40 199.15,5.15 200.00,3.73"/>
    </edge>
    <edge id=":gneJ6_16" function="internal">
        <lane id=":gneJ6_16_0" index="0" speed="9.26" length="12.40" shape="200.00,3.73 201.40,1.40 205.15,-0.85 210.40,-1.60"/>
    </edge>
    <edge id=":gneJ6_4" function="internal">
        <lane id=":gneJ6_4_0" index="0" speed="6.51" length="9.03" shape="210.40,4.80 207.95,5.15 206.20,6.20 205.15,7.95 204.80,10.40"/>
    </edge>
    <edge id=":gneJ6_5" function="internal">
        <lane id=":gneJ6_5_0" index="0" speed="13.89" length="20.80" shape="210.40,4.80 189.60,4.80"/>
        <lane id=":gneJ6_5_1" index="1" speed="13.89" length="20.80" shape="210.40,1.60 189.60,1.60"/>
    </edge>
    <edge id=":gneJ6_7" function="internal">
        <lane id=":gneJ6_7_0" index="0" speed="9.26" length="6.96" shape="210.40,1.60 205.15,0.85 203.73,0.00"/>
    </edge>
    <edge id=":gneJ6_17" function="internal">
        <lane id=":gneJ6_17_0" index="0" speed="9.26" length="12.40" shape="203.73,0.00 201.40,-1.40 199.15,-5.15 198.40,-10.40"/>
    </edge>
    <edge id=":gneJ6_8" function="internal">
        <lane id=":gneJ6_8_0" index="0" speed="6.51" length="9.03" shape="204.80,-10.40 205.15,-7.95 206.20,-6.20 207.95,-5.15 210.40,-4.80"/>
    </edge>
    <edge id=":gneJ6_9" function="internal">
        <lane id=":gneJ6_9_0" index="0" speed="13.89" length="20.80" shape="204.80,-10.40 204.80,10.40"/>
        <lane id=":gneJ6_9_1" index="1" speed="13.89" length="20.80" shape="201.60,-10.40 201.60,10.40"/>
    </edge>
    <edge id=":gneJ6_11" function="internal">
        <lane id=":gneJ6_11_0" index="0" speed="9.26" length="6.96" shape="201.60,-10.40 200.85,-5.15 200.00,-3.73"/>
    </edge>
    <edge id=":gneJ6_18" function="internal">
        <lane id=":gneJ6_18_0" index="0" speed="9.26" length="12.40" shape="200.00,-3.73 198.60,-1.40 194.85,0.85 189.60,1.60"/>
    </edge>
    <edge id=":gneJ6_12" function="internal">
        <lane id=":gneJ6_12_0" index="0" speed="6.51" length="9.03" shape="189.60,-4.80 192.05,-5.15 193.80,-6.20 194.85,-7.95 195.20,-10.40"/>
    </edge>
    <edge id=":gneJ6_13" function="internal">
        <lane id=":gneJ6_13_0" index="0" speed="13.89" length="20.80" shape="189.60,-4.80 210.40,-4.80"/>
        <lane id=":gneJ6_13_1" index="1" speed="13.89" length="20.80" shape="189.60,-1.60 210.40,-1.60"/>
    </edge>
    <edge id=":gneJ6_15" function="internal">
        <lane id=":gneJ6_15_0" index="0" speed="9.26" length="6.96" shape="189.60,-1.60 194.85,-0.85 196.27,-0.00"/>
    </edge>
    <edge id=":gneJ6_19" function="internal">
        <lane id=":gneJ6_19_0" index="0" speed="9.26" length="12.40" shape="196.27,-0.00 198.60,1.40 200.85,5.15 201.60,10.40"/>
    </edge>

    <edge id="-gneE0" from="gneJ1" to="gneJ0" priority="-1">
        <lane id="-gneE0_0" index="0" speed="13.89" length="189.60" shape="-210.40,4.80 -400.00,4.80"/>
        <lane id="-gneE0_1" index="1" speed="13.89" length="189.60" shape="-210.40,1.60 -400.00,1.60"/>
    </edge>
    <edge id="-gneE1" from="gneJ2" to="gneJ1" priority="-1">
        <lane id="-gneE1_0" index="0" speed="13.89" length="189.60" shape="-204.80,200.00 -204.80,10.40"/>
        <lane id="-gneE1_1" index="1" speed="13.89" length="189.60" shape="-201.60,200.00 -201.60,10.40"/>
    </edge>
    <edge id="-gneE2" from="gneJ3" to="gneJ1" priority="-1">
        <lane id="-gneE2_0" index="0" speed="13.89" length="189.60" shape="-195.20,-200.00 -195.20,-10.40"/>
        <lane id="-gneE2_1" index="1" speed="13.89" length="189.60" shape="-198.40,-200.00 -198.40,-10.40"/>
    </edge>
    <edge id="-gneE3" from="gneJ4" to="gneJ1" priority="-1">
        <lane id="-gneE3_0" index="0" speed="13.89" length="179.20" shape="-10.40,4.80 -189.60,4.80"/>
        <lane id="-gneE3_1" index="1" speed="13.89" length="179.20" shape="-10.40,1.60 -189.60,1.60"/>
    </edge>
    <edge id="-gneE4" from="gneJ5" to="gneJ4" priority="-1">
        <lane id="-gneE4_0" index="0" speed="13.89" length="189.60" shape="-4.80,200.00 -4.80,10.40"/>
        <lane id="-gneE4_1" index="1" speed="13.89" length="189.60" shape="-1.60,200.00 -1.60,10.40"/>
    </edge>
    <edge id="-gneE5" from="gneJ6" to="gneJ4" priority="-1">
        <lane id="-gneE5_0" index="0" speed="13.89" length="179.20" shape="189.60,4.80 10.40,4.80"/>
        <lane id="-gneE5_1" index="1" speed="13.89" length="179.20" shape="189.60,1.60 10.40,1.60"/>
    </edge>
    <edge id="-gneE6" from="gneJ7" to="gneJ4" priority="-1">
        <lane id="-gneE6_0" index="0" speed="13.89" length="189.60" shape="4.80,-200.00 4.80,-10.40"/>
        <lane id="-gneE6_1" index="1" speed="13.89" length="189.60" shape="1.60,-200.00 1.60,-10.40"/>
    </edge>
    <edge id="-gneE7" from="gneJ8" to="gneJ6" priority="-1">
        <lane id="-gneE7_0" index="0" speed="13.89" length="189.60" shape="195.20,200.00 195.20,10.40"/>
        <lane id="-gneE7_1" index="1" speed="13.89" length="189.60" shape="198.40,200.00 198.40,10.40"/>
    </edge>
    <edge id="-gneE8" from="gneJ9" to="gneJ6" priority="-1">
        <lane id="-gneE8_0" index="0" speed="13.89" length="189.60" shape="204.80,-200.00 204.80,-10.40"/>
        <lane id="-gneE8_1" index="1" speed="13.89" length="189.60" shape="201.60,-200.00 201.60,-10.40"/>
    </edge>
    <edge id="-gneE9" from="gneJ10" to="gneJ6" priority="-1">
        <lane id="-gneE9_0" index="0" speed="13.89" length="189.60" shape="400.00,4.80 210.40,4.80"/>
        <lane id="-gneE9_1" index="1" speed="13.89" length="189.60" shape="400.00,1.60 210.40,1.60"/>
    </edge>
    <edge id="gneE0" from="gneJ0" to="gneJ1" priority="-1">
        <lane id="gneE0_0" index="0" speed="13.89" length="189.60" shape="-400.00,-4.80 -210.40,-4.80"/>
        <lane id="gneE0_1" index="1" speed="13.89" length="189.60" shape="-400.00,-1.60 -210.40,-1.60"/>
    </edge>
    <edge id="gneE1" from="gneJ1" to="gneJ2" priority="-1">
        <lane id="gneE1_0" index="0" speed="13.89" length="189.60" shape="-195.20,10.40 -195.20,200.00"/>
        <lane id="gneE1_1" index="1" speed="13.89" length="189.60" shape="-198.40,10.40 -198.40,200.00"/>
    </edge>
    <edge id="gneE2" from="gneJ1" to="gneJ3" priority="-1">
        <lane id="gneE2_0" index="0" speed="13.89" length="189.60" shape="-204.80,-10.40 -204.80,-200.00"/>
        <lane id="gneE2_1" index="1" speed="13.89" length="189.60" shape="-201.60,-10.40 -201.60,-200.00"/>
    </edge>
    <edge id="gneE3" from="gneJ1" to="gneJ4" priority="-1">
        <lane id="gneE3_0" index="0" speed="13.89" length="179.20" shape="-189.60,-4.80 -10.40,-4.80"/>
        <lane id="gneE3_1" index="1" speed="13.89" length="179.20" shape="-189.60,-1.60 -10.40,-1.60"/>
    </edge>
    <edge id="gneE4" from="gneJ4" to="gneJ5" priority="-1">
        <lane id="gneE4_0" index="0" speed="13.89" length="189.60" shape="4.80,10.40 4.80,200.00"/>
        <lane id="gneE4_1" index="1" speed="13.89" length="189.60" shape="1.60,10.40 1.60,200.00"/>
    </edge>
    <edge id="gneE5" from="gneJ4" to="gneJ6" priority="-1">
        <lane id="gneE5_0" index="0" speed="13.89" length="179.20" shape="10.40,-4.80 189.60,-4.80"/>
        <lane id="gneE5_1" index="1" speed="13.89" length="179.20" shape="10.40,-1.60 189.60,-1.60"/>
    </edge>
    <edge id="gneE6" from="gneJ4" to="gneJ7" priority="-1">
        <lane id="gneE6_0" index="0" speed="13.89" length="189.60" shape="-4.80,-10.40 -4.80,-200.00"/>
        <lane id="gneE6_1" index="1" speed="13.89" length="189.60" shape="-1.60,-10.40 -1.60,-200.00"/>
    </edge>
    <edge id="gneE7" from="gneJ6" to="gneJ8" priority="-1">
        <lane id="gneE7_0" index="0" speed="13.89" length="189.60" shape="204.80,10.40 204.80,200.00"/>
        <lane id="gneE7_1" index="1" speed="13.89" length="189.60" shape="201.60,10.40 201.60,200.00"/>
    </edge>
    <edge id="gneE8" from="gneJ6" to="gneJ9" priority="-1">
        <lane id="gneE8_0" index="0" speed="13.89" length="189.60" shape="195.20,-10.40 195.20,-200.00"/>
        <lane id="gneE8_1" index="1" speed="13.89" length="189.60" shape="198.40,-10.40 198.40,-200.00"/>
    </edge>
    <edge id="gneE9" from="gneJ6" to="gneJ10" priority="-1">
        <lane id="gneE9_0" index="0" speed="13.89" length="189.60" shape="210.40,-4.80 400.00,-4.80"/>
        <lane id="gneE9_1" index="1" speed="13.89" length="189.60" shape="210.40,-1.60 400.00,-1.60"/>
    </edge>

    <tlLogic id="gneJ1" type="static" programID="0" offset="0">
        <phase duration="42" state="GGGgrrrrGGGgrrrr"/>
        <phase duration="3"  state="yyyyrrrryyyyrrrr"/>
        <phase duration="42" state="rrrrGGGgrrrrGGGg"/>
        <phase duration="3"  state="rrrryyyyrrrryyyy"/>
    </tlLogic>
    <tlLogic id="gneJ4" type="static" programID="0" offset="0">
        <phase duration="42" state="GGGgrrrrGGGgrrrr"/>
        <phase duration="3"  state="yyyyrrrryyyyrrrr"/>
        <phase duration="42" state="rrrrGGGgrrrrGGGg"/>
        <phase duration="3"  state="rrrryyyyrrrryyyy"/>
    </tlLogic>
    <tlLogic id="gneJ6" type="static" programID="0" offset="0">
        <phase duration="42" state="GGGgrrrrGGGgrrrr"/>
        <phase duration="3"  state="yyyyrrrryyyyrrrr"/>
        <phase duration="42" state="rrrrGGGgrrrrGGGg"/>
        <phase duration="3"  state="rrrryyyyrrrryyyy"/>
    </tlLogic>

    <junction id="gneJ0" type="dead_end" x="-400.00" y="0.00" incLanes="-gneE0_0 -gneE0_1" intLanes="" shape="-400.00,0.00 -400.00,6.40 -400.00,0.00"/>
    <junction id="gneJ1" type="traffic_light" x="-200.00" y="0.00" incLanes="-gneE1_0 -gneE1_1 -gneE3_0 -gneE3_1 -gneE2_0 -gneE2_1 gneE0_0 gneE0_1" intLanes=":gneJ1_0_0 :gneJ1_1_0 :gneJ1_1_1 :gneJ1_16_0 :gneJ1_4_0 :gneJ1_5_0 :gneJ1_5_1 :gneJ1_17_0 :gneJ1_8_0 :gneJ1_9_0 :gneJ1_9_1 :gneJ1_18_0 :gneJ1_12_0 :gneJ1_13_0 :gneJ1_13_1 :gneJ1_19_0" shape="-206.40,10.40 -193.60,10.40 -193.16,8.18 -192.60,7.40 -191.82,6.84 -190.82,6.51 -189.60,6.40 -189.60,-6.40 -191.82,-6.84 -192.60,-7.40 -193.16,-8.18 -193.49,-9.18 -193.60,-10.40 -206.40,-10.40 -206.84,-8.18 -207.40,-7.40 -208.18,-6.84 -209.18,-6.51 -210.40,-6.40 -210.40,6.40 -208.18,6.84 -207.40,7.40 -206.84,8.18 -206.51,9.18">
        <request index="0"  response="0000000000000000" foes="0000000001100000" cont="0"/>
        <request index="1"  response="1000000010000000" foes="1111100011100000" cont="0"/>
        <request index="2"  response="1000000010000000" foes="1111100011100000" cont="0"/>
        <request index="3"  response="1000011010000000" foes="1110011011100000" cont="1"/>
        <request index="4"  response="0000011000000000" foes="0000011000000000" cont="0"/>
        <request index="5"  response="0000111000001111" foes="1000111000001111" cont="0"/>
        <request index="6"  response="0000111000001111" foes="1000111000001111" cont="0"/>
        <request index="7"  response="0110111000001110" foes="0110111000001110" cont="1"/>
        <request index="8"  response="0000000000000000" foes="0110000000000000" cont="0"/>
        <request index="9"  response="1000000010000000" foes="1110000011111000" cont="0"/>
        <request index="10" response="1000000010000000" foes="1110000011111000" cont="0"/>
        <request index="11" response="1000000010000110" foes="1110000011100110" cont="1"/>
        <request index="12" response="0000000000000110" foes="0000000000000110" cont="0"/>
        <request index="13" response="0000111100001110" foes="0000111110001110" cont="0"/>
        <request index="14" response="0000111100001110" foes="0000111110001110" cont="0"/>
        <request index="15" response="0000111001101110" foes="0000111001101110" cont="1"/>
    </junction>
    <junction id="gneJ10" type="dead_end" x="400.00" y="0.00" incLanes="gneE9_0 gneE9_1" intLanes="" shape="400.00,0.00 400.00,-6.40 400.00,0.00"/>
    <junction id="gneJ2" type="dead_end" x="-200.00" y="200.00" incLanes="gneE1_0 gneE1_1" intLanes="" shape="-200.00,200.00 -193.60,200.00 -200.00,200.00"/>
    <junction id="gneJ3" type="dead_end" x="-200.00" y="-200.00" incLanes="gneE2_0 gneE2_1" intLanes="" shape="-200.00,-200.00 -206.40,-200.00 -200.00,-200.00"/>
    <junction id="gneJ4" type="traffic_light" x="0.00" y="0.00" incLanes="-gneE4_0 -gneE4_1 -gneE5_0 -gneE5_1 -gneE6_0 -gneE6_1 gneE3_0 gneE3_1" intLanes=":gneJ4_0_0 :gneJ4_1_0 :gneJ4_1_1 :gneJ4_16_0 :gneJ4_4_0 :gneJ4_5_0 :gneJ4_5_1 :gneJ4_17_0 :gneJ4_8_0 :gneJ4_9_0 :gneJ4_9_1 :gneJ4_18_0 :gneJ4_12_0 :gneJ4_13_0 :gneJ4_13_1 :gneJ4_19_0" shape="-6.40,10.40 6.40,10.40 6.84,8.18 7.40,7.40 8.18,6.84 9.18,6.51 10.40,6.40 10.40,-6.40 8.18,-6.84 7.40,-7.40 6.84,-8.18 6.51,-9.18 6.40,-10.40 -6.40,-10.40 -6.84,-8.18 -7.40,-7.40 -8.18,-6.84 -9.18,-6.51 -10.40,-6.40 -10.40,6.40 -8.18,6.84 -7.40,7.40 -6.84,8.18 -6.51,9.18">
        <request index="0"  response="0000000000000000" foes="0000000001100000" cont="0"/>
        <request index="1"  response="1000000010000000" foes="1111100011100000" cont="0"/>
        <request index="2"  response="1000000010000000" foes="1111100011100000" cont="0"/>
        <request index="3"  response="1000011010000000" foes="1110011011100000" cont="1"/>
        <request index="4"  response="0000011000000000" foes="0000011000000000" cont="0"/>
        <request index="5"  response="0000111000001111" foes="1000111000001111" cont="0"/>
        <request index="6"  response="0000111000001111" foes="1000111000001111" cont="0"/>
        <request index="7"  response="0110111000001110" foes="0110111000001110" cont="1"/>
        <request index="8"  response="0000000000000000" foes="0110000000000000" cont="0"/>
        <request index="9"  response="1000000010000000" foes="1110000011111000" cont="0"/>
        <request index="10" response="1000000010000000" foes="1110000011111000" cont="0"/>
        <request index="11" response="1000000010000110" foes="1110000011100110" cont="1"/>
        <request index="12" response="0000000000000110" foes="0000000000000110" cont="0"/>
        <request index="13" response="0000111100001110" foes="0000111110001110" cont="0"/>
        <request index="14" response="0000111100001110" foes="0000111110001110" cont="0"/>
        <request index="15" response="0000111001101110" foes="0000111001101110" cont="1"/>
    </junction>
    <junction id="gneJ5" type="dead_end" x="0.00" y="200.00" incLanes="gneE4_0 gneE4_1" intLanes="" shape="0.00,200.00 6.40,200.00 0.00,200.00"/>
    <junction id="gneJ6" type="traffic_light" x="200.00" y="0.00" incLanes="-gneE7_0 -gneE7_1 -gneE9_0 -gneE9_1 -gneE8_0 -gneE8_1 gneE5_0 gneE5_1" intLanes=":gneJ6_0_0 :gneJ6_1_0 :gneJ6_1_1 :gneJ6_16_0 :gneJ6_4_0 :gneJ6_5_0 :gneJ6_5_1 :gneJ6_17_0 :gneJ6_8_0 :gneJ6_9_0 :gneJ6_9_1 :gneJ6_18_0 :gneJ6_12_0 :gneJ6_13_0 :gneJ6_13_1 :gneJ6_19_0" shape="193.60,10.40 206.40,10.40 206.84,8.18 207.40,7.40 208.18,6.84 209.18,6.51 210.40,6.40 210.40,-6.40 208.18,-6.84 207.40,-7.40 206.84,-8.18 206.51,-9.18 206.40,-10.40 193.60,-10.40 193.16,-8.18 192.60,-7.40 191.82,-6.84 190.82,-6.51 189.60,-6.40 189.60,6.40 191.82,6.84 192.60,7.40 193.16,8.18 193.49,9.18">
        <request index="0"  response="0000000000000000" foes="0000000001100000" cont="0"/>
        <request index="1"  response="1000000010000000" foes="1111100011100000" cont="0"/>
        <request index="2"  response="1000000010000000" foes="1111100011100000" cont="0"/>
        <request index="3"  response="1000011010000000" foes="1110011011100000" cont="1"/>
        <request index="4"  response="0000011000000000" foes="0000011000000000" cont="0"/>
        <request index="5"  response="0000111000001111" foes="1000111000001111" cont="0"/>
        <request index="6"  response="0000111000001111" foes="1000111000001111" cont="0"/>
        <request index="7"  response="0110111000001110" foes="0110111000001110" cont="1"/>
        <request index="8"  response="0000000000000000" foes="0110000000000000" cont="0"/>
        <request index="9"  response="1000000010000000" foes="1110000011111000" cont="0"/>
        <request index="10" response="1000000010000000" foes="1110000011111000" cont="0"/>
        <request index="11" response="1000000010000110" foes="1110000011100110" cont="1"/>
        <request index="12" response="0000000000000110" foes="0000000000000110" cont="0"/>
        <request index="13" response="0000111100001110" foes="0000111110001110" cont="0"/>
        <request index="14" response="0000111100001110" foes="0000111110001110" cont="0"/>
        <request index="15" response="0000111001101110" foes="0000111001101110" cont="1"/>
    </junction>
    <junction id="gneJ7" type="dead_end" x="0.00" y="-200.00" incLanes="gneE6_0 gneE6_1" intLanes="" shape="0.00,-200.00 -6.40,-200.00 0.00,-200.00"/>
    <junction id="gneJ8" type="dead_end" x="200.00" y="200.00" incLanes="gneE7_0 gneE7_1" intLanes="" shape="200.00,200.00 206.40,200.00 200.00,200.00"/>
    <junction id="gneJ9" type="dead_end" x="200.00" y="-200.00" incLanes="gneE8_0 gneE8_1" intLanes="" shape="200.00,-200.00 193.60,-200.00 200.00,-200.00"/>

    <junction id=":gneJ1_16_0" type="internal" x="-200.00" y="3.73" incLanes=":gneJ1_3_0 -gneE2_0 -gneE2_1" intLanes=":gneJ1_5_0 :gneJ1_5_1 :gneJ1_7_0 :gneJ1_8_0 :gneJ1_9_0 :gneJ1_9_1 :gneJ1_13_0 :gneJ1_13_1 :gneJ1_15_0"/>
    <junction id=":gneJ1_17_0" type="internal" x="-196.27" y="0.00" incLanes=":gneJ1_7_0 gneE0_0 gneE0_1" intLanes=":gneJ1_1_0 :gneJ1_1_1 :gneJ1_3_0 :gneJ1_9_0 :gneJ1_9_1 :gneJ1_11_0 :gneJ1_12_0 :gneJ1_13_0 :gneJ1_13_1"/>
    <junction id=":gneJ1_18_0" type="internal" x="-200.00" y="-3.73" incLanes=":gneJ1_11_0 -gneE1_0 -gneE1_1" intLanes=":gneJ1_0_0 :gneJ1_1_0 :gneJ1_1_1 :gneJ1_5_0 :gneJ1_5_1 :gneJ1_7_0 :gneJ1_13_0 :gneJ1_13_1 :gneJ1_15_0"/>
    <junction id=":gneJ1_19_0" type="internal" x="-203.73" y="-0.00" incLanes=":gneJ1_15_0 -gneE3_0 -gneE3_1" intLanes=":gneJ1_1_0 :gneJ1_1_1 :gneJ1_3_0 :gneJ1_4_0 :gneJ1_5_0 :gneJ1_5_1 :gneJ1_9_0 :gneJ1_9_1 :gneJ1_11_0"/>
    <junction id=":gneJ4_16_0" type="internal" x="-0.00" y="3.73" incLanes=":gneJ4_3_0 -gneE6_0 -gneE6_1" intLanes=":gneJ4_5_0 :gneJ4_5_1 :gneJ4_7_0 :gneJ4_8_0 :gneJ4_9_0 :gneJ4_9_1 :gneJ4_13_0 :gneJ4_13_1 :gneJ4_15_0"/>
    <junction id=":gneJ4_17_0" type="internal" x="3.73" y="0.00" incLanes=":gneJ4_7_0 gneE3_0 gneE3_1" intLanes=":gneJ4_1_0 :gneJ4_1_1 :gneJ4_3_0 :gneJ4_9_0 :gneJ4_9_1 :gneJ4_11_0 :gneJ4_12_0 :gneJ4_13_0 :gneJ4_13_1"/>
    <junction id=":gneJ4_18_0" type="internal" x="0.00" y="-3.73" incLanes=":gneJ4_11_0 -gneE4_0 -gneE4_1" intLanes=":gneJ4_0_0 :gneJ4_1_0 :gneJ4_1_1 :gneJ4_5_0 :gneJ4_5_1 :gneJ4_7_0 :gneJ4_13_0 :gneJ4_13_1 :gneJ4_15_0"/>
    <junction id=":gneJ4_19_0" type="internal" x="-3.73" y="-0.00" incLanes=":gneJ4_15_0 -gneE5_0 -gneE5_1" intLanes=":gneJ4_1_0 :gneJ4_1_1 :gneJ4_3_0 :gneJ4_4_0 :gneJ4_5_0 :gneJ4_5_1 :gneJ4_9_0 :gneJ4_9_1 :gneJ4_11_0"/>
    <junction id=":gneJ6_16_0" type="internal" x="200.00" y="3.73" incLanes=":gneJ6_3_0 -gneE8_0 -gneE8_1" intLanes=":gneJ6_5_0 :gneJ6_5_1 :gneJ6_7_0 :gneJ6_8_0 :gneJ6_9_0 :gneJ6_9_1 :gneJ6_13_0 :gneJ6_13_1 :gneJ6_15_0"/>
    <junction id=":gneJ6_17_0" type="internal" x="203.73" y="0.00" incLanes=":gneJ6_7_0 gneE5_0 gneE5_1" intLanes=":gneJ6_1_0 :gneJ6_1_1 :gneJ6_3_0 :gneJ6_9_0 :gneJ6_9_1 :gneJ6_11_0 :gneJ6_12_0 :gneJ6_13_0 :gneJ6_13_1"/>
    <junction id=":gneJ6_18_0" type="internal" x="200.00" y="-3.73" incLanes=":gneJ6_11_0 -gneE7_0 -gneE7_1" intLanes=":gneJ6_0_0 :gneJ6_1_0 :gneJ6_1_1 :gneJ6_5_0 :gneJ6_5_1 :gneJ6_7_0 :gneJ6_13_0 :gneJ6_13_1 :gneJ6_15_0"/>
    <junction id=":gneJ6_19_0" type="internal" x="196.27" y="-0.00" incLanes=":gneJ6_15_0 -gneE9_0 -gneE9_1" intLanes=":gneJ6_1_0 :gneJ6_1_1 :gneJ6_3_0 :gneJ6_4_0 :gneJ6_5_0 :gneJ6_5_1 :gneJ6_9_0 :gneJ6_9_1 :gneJ6_11_0"/>

    <connection from="-gneE1" to="-gneE0" fromLane="0" toLane="0" via=":gneJ1_0_0" tl="gneJ1" linkIndex="0" dir="r" state="O"/>
    <connection from="-gneE1" to="gneE2" fromLane="0" toLane="0" via=":gneJ1_1_0" tl="gneJ1" linkIndex="1" dir="s" state="O"/>
    <connection from="-gneE1" to="gneE2" fromLane="1" toLane="1" via=":gneJ1_1_1" tl="gneJ1" linkIndex="2" dir="s" state="O"/>
    <connection from="-gneE1" to="gneE3" fromLane="1" toLane="1" via=":gneJ1_3_0" tl="gneJ1" linkIndex="3" dir="l" state="o"/>
    <connection from="-gneE2" to="gneE3" fromLane="0" toLane="0" via=":gneJ1_8_0" tl="gneJ1" linkIndex="8" dir="r" state="O"/>
    <connection from="-gneE2" to="gneE1" fromLane="0" toLane="0" via=":gneJ1_9_0" tl="gneJ1" linkIndex="9" dir="s" state="O"/>
    <connection from="-gneE2" to="gneE1" fromLane="1" toLane="1" via=":gneJ1_9_1" tl="gneJ1" linkIndex="10" dir="s" state="O"/>
    <connection from="-gneE2" to="-gneE0" fromLane="1" toLane="1" via=":gneJ1_11_0" tl="gneJ1" linkIndex="11" dir="l" state="o"/>
    <connection from="-gneE3" to="gneE1" fromLane="0" toLane="0" via=":gneJ1_4_0" tl="gneJ1" linkIndex="4" dir="r" state="o"/>
    <connection from="-gneE3" to="-gneE0" fromLane="0" toLane="0" via=":gneJ1_5_0" tl="gneJ1" linkIndex="5" dir="s" state="o"/>
    <connection from="-gneE3" to="-gneE0" fromLane="1" toLane="1" via=":gneJ1_5_1" tl="gneJ1" linkIndex="6" dir="s" state="o"/>
    <connection from="-gneE3" to="gneE2" fromLane="1" toLane="1" via=":gneJ1_7_0" tl="gneJ1" linkIndex="7" dir="l" state="o"/>
    <connection from="-gneE4" to="-gneE3" fromLane="0" toLane="0" via=":gneJ4_0_0" tl="gneJ4" linkIndex="0" dir="r" state="O"/>
    <connection from="-gneE4" to="gneE6" fromLane="0" toLane="0" via=":gneJ4_1_0" tl="gneJ4" linkIndex="1" dir="s" state="O"/>
    <connection from="-gneE4" to="gneE6" fromLane="1" toLane="1" via=":gneJ4_1_1" tl="gneJ4" linkIndex="2" dir="s" state="O"/>
    <connection from="-gneE4" to="gneE5" fromLane="1" toLane="1" via=":gneJ4_3_0" tl="gneJ4" linkIndex="3" dir="l" state="o"/>
    <connection from="-gneE5" to="gneE4" fromLane="0" toLane="0" via=":gneJ4_4_0" tl="gneJ4" linkIndex="4" dir="r" state="o"/>
    <connection from="-gneE5" to="-gneE3" fromLane="0" toLane="0" via=":gneJ4_5_0" tl="gneJ4" linkIndex="5" dir="s" state="o"/>
    <connection from="-gneE5" to="-gneE3" fromLane="1" toLane="1" via=":gneJ4_5_1" tl="gneJ4" linkIndex="6" dir="s" state="o"/>
    <connection from="-gneE5" to="gneE6" fromLane="1" toLane="1" via=":gneJ4_7_0" tl="gneJ4" linkIndex="7" dir="l" state="o"/>
    <connection from="-gneE6" to="gneE5" fromLane="0" toLane="0" via=":gneJ4_8_0" tl="gneJ4" linkIndex="8" dir="r" state="O"/>
    <connection from="-gneE6" to="gneE4" fromLane="0" toLane="0" via=":gneJ4_9_0" tl="gneJ4" linkIndex="9" dir="s" state="O"/>
    <connection from="-gneE6" to="gneE4" fromLane="1" toLane="1" via=":gneJ4_9_1" tl="gneJ4" linkIndex="10" dir="s" state="O"/>
    <connection from="-gneE6" to="-gneE3" fromLane="1" toLane="1" via=":gneJ4_11_0" tl="gneJ4" linkIndex="11" dir="l" state="o"/>
    <connection from="-gneE7" to="-gneE5" fromLane="0" toLane="0" via=":gneJ6_0_0" tl="gneJ6" linkIndex="0" dir="r" state="O"/>
    <connection from="-gneE7" to="gneE8" fromLane="0" toLane="0" via=":gneJ6_1_0" tl="gneJ6" linkIndex="1" dir="s" state="O"/>
    <connection from="-gneE7" to="gneE8" fromLane="1" toLane="1" via=":gneJ6_1_1" tl="gneJ6" linkIndex="2" dir="s" state="O"/>
    <connection from="-gneE7" to="gneE9" fromLane="1" toLane="1" via=":gneJ6_3_0" tl="gneJ6" linkIndex="3" dir="l" state="o"/>
    <connection from="-gneE8" to="gneE9" fromLane="0" toLane="0" via=":gneJ6_8_0" tl="gneJ6" linkIndex="8" dir="r" state="O"/>
    <connection from="-gneE8" to="gneE7" fromLane="0" toLane="0" via=":gneJ6_9_0" tl="gneJ6" linkIndex="9" dir="s" state="O"/>
    <connection from="-gneE8" to="gneE7" fromLane="1" toLane="1" via=":gneJ6_9_1" tl="gneJ6" linkIndex="10" dir="s" state="O"/>
    <connection from="-gneE8" to="-gneE5" fromLane="1" toLane="1" via=":gneJ6_11_0" tl="gneJ6" linkIndex="11" dir="l" state="o"/>
    <connection from="-gneE9" to="gneE7" fromLane="0" toLane="0" via=":gneJ6_4_0" tl="gneJ6" linkIndex="4" dir="r" state="o"/>
    <connection from="-gneE9" to="-gneE5" fromLane="0" toLane="0" via=":gneJ6_5_0" tl="gneJ6" linkIndex="5" dir="s" state="o"/>
    <connection from="-gneE9" to="-gneE5" fromLane="1" toLane="1" via=":gneJ6_5_1" tl="gneJ6" linkIndex="6" dir="s" state="o"/>
    <connection from="-gneE9" to="gneE8" fromLane="1" toLane="1" via=":gneJ6_7_0" tl="gneJ6" linkIndex="7" dir="l" state="o"/>
    <connection from="gneE0" to="gneE2" fromLane="0" toLane="0" via=":gneJ1_12_0" tl="gneJ1" linkIndex="12" dir="r" state="o"/>
    <connection from="gneE0" to="gneE3" fromLane="0" toLane="0" via=":gneJ1_13_0" tl="gneJ1" linkIndex="13" dir="s" state="o"/>
    <connection from="gneE0" to="gneE3" fromLane="1" toLane="1" via=":gneJ1_13_1" tl="gneJ1" linkIndex="14" dir="s" state="o"/>
    <connection from="gneE0" to="gneE1" fromLane="1" toLane="1" via=":gneJ1_15_0" tl="gneJ1" linkIndex="15" dir="l" state="o"/>
    <connection from="gneE3" to="gneE6" fromLane="0" toLane="0" via=":gneJ4_12_0" tl="gneJ4" linkIndex="12" dir="r" state="o"/>
    <connection from="gneE3" to="gneE5" fromLane="0" toLane="0" via=":gneJ4_13_0" tl="gneJ4" linkIndex="13" dir="s" state="o"/>
    <connection from="gneE3" to="gneE5" fromLane="1" toLane="1" via=":gneJ4_13_1" tl="gneJ4" linkIndex="14" dir="s" state="o"/>
    <connection from="gneE3" to="gneE4" fromLane="1" toLane="1" via=":gneJ4_15_0" tl="gneJ4" linkIndex="15" dir="l" state="o"/>
    <connection from="gneE5" to="gneE8" fromLane="0" toLane="0" via=":gneJ6_12_0" tl="gneJ6" linkIndex="12" dir="r" state="o"/>
    <connection from="gneE5" to="gneE9" fromLane="0" toLane="0" via=":gneJ6_13_0" tl="gneJ6" linkIndex="13" dir="s" state="o"/>
    <connection from="gneE5" to="gneE9" fromLane="1" toLane="1" via=":gneJ6_13_1" tl="gneJ6" linkIndex="14" dir="s" state="o"/>
    <connection from="gneE5" to="gneE7" fromLane="1" toLane="1" via=":gneJ6_15_0" tl="gneJ6" linkIndex="15" dir="l" state="o"/>

    <connection from=":gneJ1_0" to="-gneE0" fromLane="0" toLane="0" dir="r" state="M"/>
    <connection from=":gneJ1_1" to="gneE2" fromLane="0" toLane="0" dir="s" state="M"/>
    <connection from=":gneJ1_1" to="gneE2" fromLane="1" toLane="1" dir="s" state="M"/>
    <connection from=":gneJ1_3" to="gneE3" fromLane="0" toLane="1" via=":gneJ1_16_0" dir="l" state="m"/>
    <connection from=":gneJ1_16" to="gneE3" fromLane="0" toLane="1" dir="l" state="M"/>
    <connection from=":gneJ1_4" to="gneE1" fromLane="0" toLane="0" dir="r" state="M"/>
    <connection from=":gneJ1_5" to="-gneE0" fromLane="0" toLane="0" dir="s" state="M"/>
    <connection from=":gneJ1_5" to="-gneE0" fromLane="1" toLane="1" dir="s" state="M"/>
    <connection from=":gneJ1_7" to="gneE2" fromLane="0" toLane="1" via=":gneJ1_17_0" dir="l" state="m"/>
    <connection from=":gneJ1_17" to="gneE2" fromLane="0" toLane="1" dir="l" state="M"/>
    <connection from=":gneJ1_8" to="gneE3" fromLane="0" toLane="0" dir="r" state="M"/>
    <connection from=":gneJ1_9" to="gneE1" fromLane="0" toLane="0" dir="s" state="M"/>
    <connection from=":gneJ1_9" to="gneE1" fromLane="1" toLane="1" dir="s" state="M"/>
    <connection from=":gneJ1_11" to="-gneE0" fromLane="0" toLane="1" via=":gneJ1_18_0" dir="l" state="m"/>
    <connection from=":gneJ1_18" to="-gneE0" fromLane="0" toLane="1" dir="l" state="M"/>
    <connection from=":gneJ1_12" to="gneE2" fromLane="0" toLane="0" dir="r" state="M"/>
    <connection from=":gneJ1_13" to="gneE3" fromLane="0" toLane="0" dir="s" state="M"/>
    <connection from=":gneJ1_13" to="gneE3" fromLane="1" toLane="1" dir="s" state="M"/>
    <connection from=":gneJ1_15" to="gneE1" fromLane="0" toLane="1" via=":gneJ1_19_0" dir="l" state="m"/>
    <connection from=":gneJ1_19" to="gneE1" fromLane="0" toLane="1" dir="l" state="M"/>
    <connection from=":gneJ4_0" to="-gneE3" fromLane="0" toLane="0" dir="r" state="M"/>
    <connection from=":gneJ4_1" to="gneE6" fromLane="0" toLane="0" dir="s" state="M"/>
    <connection from=":gneJ4_1" to="gneE6" fromLane="1" toLane="1" dir="s" state="M"/>
    <connection from=":gneJ4_3" to="gneE5" fromLane="0" toLane="1" via=":gneJ4_16_0" dir="l" state="m"/>
    <connection from=":gneJ4_16" to="gneE5" fromLane="0" toLane="1" dir="l" state="M"/>
    <connection from=":gneJ4_4" to="gneE4" fromLane="0" toLane="0" dir="r" state="M"/>
    <connection from=":gneJ4_5" to="-gneE3" fromLane="0" toLane="0" dir="s" state="M"/>
    <connection from=":gneJ4_5" to="-gneE3" fromLane="1" toLane="1" dir="s" state="M"/>
    <connection from=":gneJ4_7" to="gneE6" fromLane="0" toLane="1" via=":gneJ4_17_0" dir="l" state="m"/>
    <connection from=":gneJ4_17" to="gneE6" fromLane="0" toLane="1" dir="l" state="M"/>
    <connection from=":gneJ4_8" to="gneE5" fromLane="0" toLane="0" dir="r" state="M"/>
    <connection from=":gneJ4_9" to="gneE4" fromLane="0" toLane="0" dir="s" state="M"/>
    <connection from=":gneJ4_9" to="gneE4" fromLane="1" toLane="1" dir="s" state="M"/>
    <connection from=":gneJ4_11" to="-gneE3" fromLane="0" toLane="1" via=":gneJ4_18_0" dir="l" state="m"/>
    <connection from=":gneJ4_18" to="-gneE3" fromLane="0" toLane="1" dir="l" state="M"/>
    <connection from=":gneJ4_12" to="gneE6" fromLane="0" toLane="0" dir="r" state="M"/>
    <connection from=":gneJ4_13" to="gneE5" fromLane="0" toLane="0" dir="s" state="M"/>
    <connection from=":gneJ4_13" to="gneE5" fromLane="1" toLane="1" dir="s" state="M"/>
    <connection from=":gneJ4_15" to="gneE4" fromLane="0" toLane="1" via=":gneJ4_19_0" dir="l" state="m"/>
    <connection from=":gneJ4_19" to="gneE4" fromLane="0" toLane="1" dir="l" state="M"/>
    <connection from=":gneJ6_0" to="-gneE5" fromLane="0" toLane="0" dir="r" state="M"/>
    <connection from=":gneJ6_1" to="gneE8" fromLane="0" toLane="0" dir="s" state="M"/>
    <connection from=":gneJ6_1" to="gneE8" fromLane="1" toLane="1" dir="s" state="M"/>
    <connection from=":gneJ6_3" to="gneE9" fromLane="0" toLane="1" via=":gneJ6_16_0" dir="l" state="m"/>
    <connection from=":gneJ6_16" to="gneE9" fromLane="0" toLane="1" dir="l" state="M"/>
    <connection from=":gneJ6_4" to="gneE7" fromLane="0" toLane="0" dir="r" state="M"/>
    <connection from=":gneJ6_5" to="-gneE5" fromLane="0" toLane="0" dir="s" state="M"/>
    <connection from=":gneJ6_5" to="-gneE5" fromLane="1" toLane="1" dir="s" state="M"/>
    <connection from=":gneJ6_7" to="gneE8" fromLane="0" toLane="1" via=":gneJ6_17_0" dir="l" state="m"/>
    <connection from=":gneJ6_17" to="gneE8" fromLane="0" toLane="1" dir="l" state="M"/>
    <connection from=":gneJ6_8" to="gneE9" fromLane="0" toLane="0" dir="r" state="M"/>
    <connection from=":gneJ6_9" to="gneE7" fromLane="0" toLane="0" dir="s" state="M"/>
    <connection from=":gneJ6_9" to="gneE7" fromLane="1" toLane="1" dir="s" state="M"/>
    <connection from=":gneJ6_11" to="-gneE5" fromLane="0" toLane="1" via=":gneJ6_18_0" dir="l" state="m"/>
    <connection from=":gneJ6_18" to="-gneE5" fromLane="0" toLane="1" dir="l" state="M"/>
    <connection from=":gneJ6_12" to="gneE8" fromLane="0" toLane="0" dir="r" state="M"/>
    <connection from=":gneJ6_13" to="gneE9" fromLane="0" toLane="0" dir="s" state="M"/>
    <connection from=":gneJ6_13" to="gneE9" fromLane="1" toLane="1" dir="s" state="M"/>
    <connection from=":gneJ6_15" to="gneE7" fromLane="0" toLane="1" via=":gneJ6_19_0" dir="l" state="m"/>
    <connection from=":gneJ6_19" to="gneE7" fromLane="0" toLane="1" dir="l" state="M"/>

</net>
